setup.py
dm/__init__.py
dm.zopepatches.xmlrpc.egg-info/PKG-INFO
dm.zopepatches.xmlrpc.egg-info/SOURCES.txt
dm.zopepatches.xmlrpc.egg-info/dependency_links.txt
dm.zopepatches.xmlrpc.egg-info/namespace_packages.txt
dm.zopepatches.xmlrpc.egg-info/not-zip-safe
dm.zopepatches.xmlrpc.egg-info/requires.txt
dm.zopepatches.xmlrpc.egg-info/top_level.txt
dm/zopepatches/__init__.py
dm/zopepatches/xmlrpc/README.txt
dm/zopepatches/xmlrpc/VERSION.txt
dm/zopepatches/xmlrpc/__init__.py
dm/zopepatches/xmlrpc/publisher/__init__.py
dm/zopepatches/xmlrpc/publisher/interfaces.py