Metadata-Version: 1.0
Name: dm.zopepatches.xmlrpc
Version: 1.0
Summary: Control whether Zope interprets a request as xmlrpc.
Home-page: http://pypi.python.org/pypi/dm.zopepatches.xmlrpc
Author: Dieter Maurer
Author-email: dieter@handshake.de
License: ZPL
Keywords: application development web xmlrpc Zope
Platform: UNKNOWN
Classifier: Development Status :: 5 - Production/Stable
Classifier: Intended Audience :: Developers
Classifier: License :: OSI Approved :: Zope Public License
Classifier: Framework :: Zope2
Classifier: Operating System :: OS Independent
Classifier: Programming Language :: Python
Classifier: Topic :: Utilities
